fsdicts/__init__.py
fsdicts/bunch.py
fsdicts/database.py
fsdicts/dictionary.py
fsdicts/encoders.py
fsdicts/lock.py
fsdicts/mapping.py
fsdicts/storage.py
fsdicts-0.6.0.dist-info/LICENSE
fsdicts-0.6.0.dist-info/METADATA
fsdicts-0.6.0.dist-info/WHEEL
fsdicts-0.6.0.dist-info/top_level.txt
fsdicts-0.6.0.dist-info/RECORD
