Metadata-Version: 2.1
Name: fsdicts
Version: 0.6.0
Summary: A simple library for file-system synced dictionaries.
Maintainer-email: Nadav Tasher <hey@nadav.app>
License: MIT License
Project-URL: Homepage, https://github.com/NadavTasher/FSDicts
Keywords: database,filesystem
Classifier: License :: OSI Approved :: MIT License
Classifier: Programming Language :: Python
Classifier: Programming Language :: Python :: 3
License-File: LICENSE
